minigram/__init__.py
minigram/td.py
minigram-0.1.dist-info/LICENSE
minigram-0.1.dist-info/METADATA
minigram-0.1.dist-info/WHEEL
minigram-0.1.dist-info/top_level.txt
minigram-0.1.dist-info/RECORD
